treinta_ms_utils/__init__.py
treinta_ms_utils/core.py
treinta_ms_utils-1.4.4.dist-info/LICENSE
treinta_ms_utils-1.4.4.dist-info/METADATA
treinta_ms_utils-1.4.4.dist-info/WHEEL
treinta_ms_utils-1.4.4.dist-info/top_level.txt
treinta_ms_utils-1.4.4.dist-info/RECORD
