Metadata-Version: 2.1
Name: treinta_ms_utils
Version: 1.4.4
Summary: paquete que permite a los microservicios interaccionar con otros MS
Author: cristian.pinela
Author-email: cristian.pinela@treinta.co
License: LICENSE
License-File: LICENSE
Requires-Dist: boto3
Requires-Dist: botocore
Requires-Dist: pytz
